pywrong/node_package.py
pywrong/node_package_manager.py
pywrong/node_project.py
pywrong/nodejs.py
pywrong/server.py
pywrong/utils.py
pywrong-0.0.2.dist-info/LICENSE
pywrong-0.0.2.dist-info/METADATA
pywrong-0.0.2.dist-info/WHEEL
pywrong-0.0.2.dist-info/entry_points.txt
pywrong-0.0.2.dist-info/RECORD
