Metadata-Version: 2.1
Name: pywrong
Version: 0.0.2
Summary: A wrapper for pyright
License: GPL-3
Author: Amit Prakash Ambasta
Author-email: amit.prakash.ambasta@gmail.com
Requires-Python: >=3.8,<4.0
Classifier: License :: Other/Proprietary License
Classifier: Programming Language :: Python :: 3
Classifier: Programming Language :: Python :: 3.8
Classifier: Programming Language :: Python :: 3.9
Classifier: Programming Language :: Python :: 3.10
Classifier: Programming Language :: Python :: 3.11
Provides-Extra: debug
Requires-Dist: ipdb (>=0.13.11,<0.14.0) ; extra == "debug"
Requires-Dist: requests (>=2.28.2,<3.0.0)
Requires-Dist: semantic-version (>=2.10.0,<3.0.0)
Requires-Dist: typeguard (>=3.0.0b2,<4.0.0)
